[[0.05777,{"lines":{"0":[["tv@apu:~/src/erlisch$                                                                                                                     ",{}]],"1":[["                                                                                                                                          ",{}]],"2":[["                                                                                                                                          ",{}]],"3":[["                                                                                                                                          ",{}]],"4":[["                                                                                                                                          ",{}]],"5":[["                                                                                                                                          ",{}]],"6":[["                                                                                                                                          ",{}]],"7":[["                                                                                                                                          ",{}]],"8":[["                                                                                                                                          ",{}]],"9":[["                                                                                                                                          ",{}]],"10":[["                                                                                                                                          ",{}]],"11":[["                                                                                                                                          ",{}]],"12":[["                                                                                                                                          ",{}]],"13":[["                                                                                                                                          ",{}]],"14":[["                                                                                                                                          ",{}]],"15":[["                                                                                                                                          ",{}]],"16":[["                                                                                                                                          ",{}]],"17":[["                                                                                                                                          ",{}]],"18":[["                                                                                                                                          ",{}]],"19":[["                                                                                                                                          ",{}]],"20":[["                                                                                                                                          ",{}]],"21":[["                                                                                                                                          ",{}]],"22":[["                                                                                                                                          ",{}]],"23":[["                                                                                                                                          ",{}]],"24":[["                                                                                                                                          ",{}]],"25":[["                                                                                                                                          ",{}]],"26":[["                                                                                                                                          ",{}]],"27":[["                                                                                                                                          ",{}]],"28":[["                                                                                                                                          ",{}]],"29":[["                                                                                                                                          ",{}]],"30":[["                                                                                                                                          ",{}]],"31":[["                                                                                                                                          ",{}]],"32":[["                                                                                                                                          ",{}]],"33":[["                                                                                                                                          ",{}]],"34":[["                                                                                                                                          ",{}]],"35":[["                                                                                                                                          ",{}]],"36":[["                                                                                                                                          ",{}]],"37":[["                                                                                                                                          ",{}]],"38":[["                                                                                                                                          ",{}]],"39":[["                                                                                                                                          ",{}]],"40":[["                                                                                                                                          ",{}]],"41":[["                                                                                                                                          ",{}]],"42":[["                                                                                                                                          ",{}]],"43":[["                                                                                                                                          ",{}]],"44":[["                                                                                                                                          ",{}]],"45":[["                                                                                                                                          ",{}]]},"cursor":{"x":22,"y":0,"visible":true}}],[0.399897,{"lines":{"0":[["tv@apu:~/src/erlisch$ r                                                                                                                   ",{}]]},"cursor":{"x":23}}],[0.052286,{"lines":{"0":[["tv@apu:~/src/erlisch$ rm                                                                                                                  ",{}]]},"cursor":{"x":24}}],[0.122975,{"cursor":{"x":25}}],[0.366219,{"lines":{"0":[["tv@apu:~/src/erlisch$ rm *                                                                                                                ",{}]]},"cursor":{"x":26}}],[0.318983,{"cursor":{"x":0,"y":1}}],[0.001819,{"lines":{"1":[["tv@apu:~/src/erlisch$                                                                                                                     ",{}]]},"cursor":{"x":22}}],[8.882130999999999,{"lines":{"1":[["tv@apu:~/src/erlisch$ w                                                                                                                   ",{}]]},"cursor":{"x":23}}],[0.112017,{"lines":{"1":[["tv@apu:~/src/erlisch$ wg                                                                                                                  ",{}]]},"cursor":{"x":24}}],[0.194541,{"lines":{"1":[["tv@apu:~/src/erlisch$ wge                                                                                                                 ",{}]]},"cursor":{"x":25}}],[0.067842,{"lines":{"1":[["tv@apu:~/src/erlisch$ wget                                                                                                                ",{}]]},"cursor":{"x":26}}],[0.099796,{"cursor":{"x":27}}],[0.417589,{"lines":{"1":[["tv@apu:~/src/erlisch$ wget https://dl.dropboxusercontent.com/u/26332463/TestForKvisle/TestForKvisle/Program.cs                            ",{}]]},"cursor":{"x":110}}],[0.427112,{"cursor":{"x":0,"y":2}}],[0.00664,{"lines":{"2":[["--2014-09-06 18:21:42--  https://dl.dropboxusercontent.com/u/26332463/TestForKvisle/TestForKvisle/Program.cs                              ",{}]],"3":[["Resolving dl.dropboxusercontent.com (dl.dropboxusercontent.com)...                                                                        ",{}]]},"cursor":{"x":67,"y":3}}],[0.010118,{"lines":{"3":[["Resolving dl.dropboxusercontent.com (dl.dropboxusercontent.com)... 54.225.184.81, 54.235.143.202, 54.235.147.68, ...                      ",{}]],"4":[["Connecting to dl.dropboxusercontent.com (dl.dropboxusercontent.com)|54.225.184.81|:443...                                                 ",{}]]},"cursor":{"x":90,"y":4}}],[0.124046,{"lines":{"4":[["Connecting to dl.dropboxusercontent.com (dl.dropboxusercontent.com)|54.225.184.81|:443... connected.                                      ",{}]]},"cursor":{"x":0,"y":5}}],[0.259571,{"lines":{"5":[["HTTP request sent, awaiting response...                                                                                                   ",{}]]},"cursor":{"x":40}}],[0.29964,{"lines":{"5":[["HTTP request sent, awaiting response... 200 OK                                                                                            ",{}]],"6":[["Length: 880 [text/plain]                                                                                                                  ",{}]],"7":[["Saving to: ‘Program.cs’                                                                                                                   ",{}]],"9":[["100%[================================================================================================>] 880         --.-K/s   in 0s       ",{}]],"11":[["2014-09-06 18:21:42 (133 MB/s) - ‘Program.cs’ saved [880/880]                                                                             ",{}]]},"cursor":{"x":0,"y":13}}],[0.000369,{"lines":{"13":[["tv@apu:~/src/erlisch$                                                                                                                     ",{}]]},"cursor":{"x":22}}],[0.730596,{"lines":{"13":[["tv@apu:~/src/erlisch$ c                                                                                                                   ",{}]]},"cursor":{"x":23}}],[0.07570300000000001,{"lines":{"13":[["tv@apu:~/src/erlisch$ ca                                                                                                                  ",{}]]},"cursor":{"x":24}}],[0.282962,{"lines":{"13":[["tv@apu:~/src/erlisch$ cat                                                                                                                 ",{}]]},"cursor":{"x":25}}],[0.131988,{"cursor":{"x":26}}],[0.280612,{"lines":{"13":[["tv@apu:~/src/erlisch$ cat P                                                                                                               ",{}]]},"cursor":{"x":27}}],[0.67302,{"lines":{"13":[["tv@apu:~/src/erlisch$ cat Program.cs                                                                                                      ",{}]]},"cursor":{"x":37}}],[0.453962,{"cursor":{"x":0,"y":14}}],[0.001636,{"lines":{"0":[["Resolving dl.dropboxusercontent.com (dl.dropboxusercontent.com)... 54.225.184.81, 54.235.143.202, 54.235.147.68, ...                      ",{}]],"1":[["Connecting to dl.dropboxusercontent.com (dl.dropboxusercontent.com)|54.225.184.81|:443... connected.                                      ",{}]],"2":[["HTTP request sent, awaiting response... 200 OK                                                                                            ",{}]],"3":[["Length: 880 [text/plain]                                                                                                                  ",{}]],"4":[["Saving to: ‘Program.cs’                                                                                                                   ",{}]],"5":[["                                                                                                                                          ",{}]],"6":[["100%[================================================================================================>] 880         --.-K/s   in 0s       ",{}]],"7":[["                                                                                                                                          ",{}]],"8":[["2014-09-06 18:21:42 (133 MB/s) - ‘Program.cs’ saved [880/880]                                                                             ",{}]],"9":[["                                                                                                                                          ",{}]],"10":[["tv@apu:~/src/erlisch$ cat Program.cs                                                                                                      ",{}]],"11":[["using System;                                                                                                                             ",{}]],"12":[["using System.Collections.Generic;                                                                                                         ",{}]],"13":[["using System.Diagnostics;                                                                                                                 ",{}]],"15":[["namespace TestForKvisle {                                                                                                                 ",{}]],"16":[["    class Program {                                                                                                                       ",{}]],"17":[["        static void Main(string[] args) {                                                                                                 ",{}]],"18":[["            int total = 0;                                                                                                                ",{}]],"19":[["            Stopwatch sw = new Stopwatch();                                                                                               ",{}]],"20":[["            List<int> list = new List<int>();                                                                                             ",{}]],"22":[["            Console.WriteLine(\"Hello Kvisle\");                                                                                            ",{}]],"24":[["            for (int i = 1; i <= 1000000; ++i) {                                                                                          ",{}]],"25":[["                list.Add(i);                                                                                                              ",{}]],"26":[["            }                                                                                                                             ",{}]],"28":[["            sw.Start();                                                                                                                   ",{}]],"29":[["            /*foreach (int i in list) {                                                                                                   ",{}]],"30":[["                total += i;                                                                                                               ",{}]],"31":[["            }*/                                                                                                                           ",{}]],"32":[["            for (int i = 0; i < list.Count; ++i) {                                                                                        ",{}]],"33":[["                total += list[i];                                                                                                         ",{}]],"34":[["            }                                                                                                                             ",{}]],"35":[["            sw.Stop();                                                                                                                    ",{}]],"37":[["            Console.WriteLine(\"Total: \" + total);                                                                                         ",{}]],"38":[["            Console.WriteLine(\"Took \" + sw.ElapsedMilliseconds + \"ms!\");                                                                  ",{}]],"39":[["            Console.WriteLine(\"\");                                                                                                        ",{}]],"42":[["        }                                                                                                                                 ",{}]],"43":[["    }                                                                                                                                     ",{}]],"44":[["}                                                                                                                                         ",{}]],"45":[["tv@apu:~/src/erlisch$                                                                                                                     ",{}]]},"cursor":{"x":22,"y":45}}],[2.258063,{"lines":{"45":[["tv@apu:~/src/erlisch$ m                                                                                                                   ",{}]]},"cursor":{"x":23}}],[0.261963,{"lines":{"45":[["tv@apu:~/src/erlisch$ ms                                                                                                                  ",{}]]},"cursor":{"x":24}}],[0.180186,{"lines":{"45":[["tv@apu:~/src/erlisch$ msc                                                                                                                 ",{}]]},"cursor":{"x":25}}],[0.302121,{"cursor":{"x":26}}],[0.206758,{"lines":{"45":[["tv@apu:~/src/erlisch$ msc Program.cs                                                                                                      ",{}]]},"cursor":{"x":37}}],[1.391741,{"lines":{"0":[["Connecting to dl.dropboxusercontent.com (dl.dropboxusercontent.com)|54.225.184.81|:443... connected.                                      ",{}]],"1":[["HTTP request sent, awaiting response... 200 OK                                                                                            ",{}]],"2":[["Length: 880 [text/plain]                                                                                                                  ",{}]],"3":[["Saving to: ‘Program.cs’                                                                                                                   ",{}]],"4":[["                                                                                                                                          ",{}]],"5":[["100%[================================================================================================>] 880         --.-K/s   in 0s       ",{}]],"6":[["                                                                                                                                          ",{}]],"7":[["2014-09-06 18:21:42 (133 MB/s) - ‘Program.cs’ saved [880/880]                                                                             ",{}]],"8":[["                                                                                                                                          ",{}]],"9":[["tv@apu:~/src/erlisch$ cat Program.cs                                                                                                      ",{}]],"10":[["using System;                                                                                                                             ",{}]],"11":[["using System.Collections.Generic;                                                                                                         ",{}]],"12":[["using System.Diagnostics;                                                                                                                 ",{}]],"13":[["                                                                                                                                          ",{}]],"14":[["namespace TestForKvisle {                                                                                                                 ",{}]],"15":[["    class Program {                                                                                                                       ",{}]],"16":[["        static void Main(string[] args) {                                                                                                 ",{}]],"17":[["            int total = 0;                                                                                                                ",{}]],"18":[["            Stopwatch sw = new Stopwatch();                                                                                               ",{}]],"19":[["            List<int> list = new List<int>();                                                                                             ",{}]],"20":[["                                                                                                                                          ",{}]],"21":[["            Console.WriteLine(\"Hello Kvisle\");                                                                                            ",{}]],"22":[["                                                                                                                                          ",{}]],"23":[["            for (int i = 1; i <= 1000000; ++i) {                                                                                          ",{}]],"24":[["                list.Add(i);                                                                                                              ",{}]],"25":[["            }                                                                                                                             ",{}]],"26":[["                                                                                                                                          ",{}]],"27":[["            sw.Start();                                                                                                                   ",{}]],"28":[["            /*foreach (int i in list) {                                                                                                   ",{}]],"29":[["                total += i;                                                                                                               ",{}]],"30":[["            }*/                                                                                                                           ",{}]],"31":[["            for (int i = 0; i < list.Count; ++i) {                                                                                        ",{}]],"32":[["                total += list[i];                                                                                                         ",{}]],"33":[["            }                                                                                                                             ",{}]],"34":[["            sw.Stop();                                                                                                                    ",{}]],"35":[["                                                                                                                                          ",{}]],"36":[["            Console.WriteLine(\"Total: \" + total);                                                                                         ",{}]],"37":[["            Console.WriteLine(\"Took \" + sw.ElapsedMilliseconds + \"ms!\");                                                                  ",{}]],"38":[["            Console.WriteLine(\"\");                                                                                                        ",{}]],"39":[["                                                                                                                                          ",{}]],"41":[["        }                                                                                                                                 ",{}]],"42":[["    }                                                                                                                                     ",{}]],"43":[["}                                                                                                                                         ",{}]],"44":[["tv@apu:~/src/erlisch$ msc Program.cs                                                                                                      ",{}]],"45":[["                                                                                                                                          ",{}]]},"cursor":{"x":0}}],[0.073229,{"lines":{"0":[["Length: 880 [text/plain]                                                                                                                  ",{}]],"1":[["Saving to: ‘Program.cs’                                                                                                                   ",{}]],"2":[["                                                                                                                                          ",{}]],"3":[["100%[================================================================================================>] 880         --.-K/s   in 0s       ",{}]],"5":[["2014-09-06 18:21:42 (133 MB/s) - ‘Program.cs’ saved [880/880]                                                                             ",{}]],"7":[["tv@apu:~/src/erlisch$ cat Program.cs                                                                                                      ",{}]],"8":[["using System;                                                                                                                             ",{}]],"9":[["using System.Collections.Generic;                                                                                                         ",{}]],"10":[["using System.Diagnostics;                                                                                                                 ",{}]],"11":[["                                                                                                                                          ",{}]],"12":[["namespace TestForKvisle {                                                                                                                 ",{}]],"13":[["    class Program {                                                                                                                       ",{}]],"14":[["        static void Main(string[] args) {                                                                                                 ",{}]],"15":[["            int total = 0;                                                                                                                ",{}]],"16":[["            Stopwatch sw = new Stopwatch();                                                                                               ",{}]],"17":[["            List<int> list = new List<int>();                                                                                             ",{}]],"18":[["                                                                                                                                          ",{}]],"19":[["            Console.WriteLine(\"Hello Kvisle\");                                                                                            ",{}]],"21":[["            for (int i = 1; i <= 1000000; ++i) {                                                                                          ",{}]],"22":[["                list.Add(i);                                                                                                              ",{}]],"23":[["            }                                                                                                                             ",{}]],"24":[["                                                                                                                                          ",{}]],"25":[["            sw.Start();                                                                                                                   ",{}]],"26":[["            /*foreach (int i in list) {                                                                                                   ",{}]],"27":[["                total += i;                                                                                                               ",{}]],"28":[["            }*/                                                                                                                           ",{}]],"29":[["            for (int i = 0; i < list.Count; ++i) {                                                                                        ",{}]],"30":[["                total += list[i];                                                                                                         ",{}]],"31":[["            }                                                                                                                             ",{}]],"32":[["            sw.Stop();                                                                                                                    ",{}]],"33":[["                                                                                                                                          ",{}]],"34":[["            Console.WriteLine(\"Total: \" + total);                                                                                         ",{}]],"35":[["            Console.WriteLine(\"Took \" + sw.ElapsedMilliseconds + \"ms!\");                                                                  ",{}]],"36":[["            Console.WriteLine(\"\");                                                                                                        ",{}]],"37":[["                                                                                                                                          ",{}]],"38":[["                                                                                                                                          ",{}]],"39":[["        }                                                                                                                                 ",{}]],"40":[["    }                                                                                                                                     ",{}]],"41":[["}                                                                                                                                         ",{}]],"42":[["tv@apu:~/src/erlisch$ msc Program.cs                                                                                                      ",{}]],"43":[["No command 'msc' found, but there are 22 similar ones                                                                                     ",{}]],"44":[["msc: command not found                                                                                                                    ",{}]]}}],[0.0094,{"lines":{"45":[["tv@apu:~/src/erlisch$                                                                                                                     ",{}]]},"cursor":{"x":22}}],[0.730678,{"lines":{"45":[["tv@apu:~/src/erlisch$ m                                                                                                                   ",{}]]},"cursor":{"x":23}}],[0.087654,{"lines":{"45":[["tv@apu:~/src/erlisch$ mc                                                                                                                  ",{}]]},"cursor":{"x":24}}],[0.039669,{"lines":{"45":[["tv@apu:~/src/erlisch$ mcs                                                                                                                 ",{}]]},"cursor":{"x":25}}],[0.153335,{"cursor":{"x":26}}],[0.142496,{"lines":{"45":[["tv@apu:~/src/erlisch$ mcs Program.cs                                                                                                      ",{}]]},"cursor":{"x":37}}],[1.052715,{"lines":{"0":[["Saving to: ‘Program.cs’                                                                                                                   ",{}]],"1":[["                                                                                                                                          ",{}]],"2":[["100%[================================================================================================>] 880         --.-K/s   in 0s       ",{}]],"3":[["                                                                                                                                          ",{}]],"4":[["2014-09-06 18:21:42 (133 MB/s) - ‘Program.cs’ saved [880/880]                                                                             ",{}]],"5":[["                                                                                                                                          ",{}]],"6":[["tv@apu:~/src/erlisch$ cat Program.cs                                                                                                      ",{}]],"7":[["using System;                                                                                                                             ",{}]],"8":[["using System.Collections.Generic;                                                                                                         ",{}]],"9":[["using System.Diagnostics;                                                                                                                 ",{}]],"10":[["                                                                                                                                          ",{}]],"11":[["namespace TestForKvisle {                                                                                                                 ",{}]],"12":[["    class Program {                                                                                                                       ",{}]],"13":[["        static void Main(string[] args) {                                                                                                 ",{}]],"14":[["            int total = 0;                                                                                                                ",{}]],"15":[["            Stopwatch sw = new Stopwatch();                                                                                               ",{}]],"16":[["            List<int> list = new List<int>();                                                                                             ",{}]],"17":[["                                                                                                                                          ",{}]],"18":[["            Console.WriteLine(\"Hello Kvisle\");                                                                                            ",{}]],"19":[["                                                                                                                                          ",{}]],"20":[["            for (int i = 1; i <= 1000000; ++i) {                                                                                          ",{}]],"21":[["                list.Add(i);                                                                                                              ",{}]],"22":[["            }                                                                                                                             ",{}]],"23":[["                                                                                                                                          ",{}]],"24":[["            sw.Start();                                                                                                                   ",{}]],"25":[["            /*foreach (int i in list) {                                                                                                   ",{}]],"26":[["                total += i;                                                                                                               ",{}]],"27":[["            }*/                                                                                                                           ",{}]],"28":[["            for (int i = 0; i < list.Count; ++i) {                                                                                        ",{}]],"29":[["                total += list[i];                                                                                                         ",{}]],"30":[["            }                                                                                                                             ",{}]],"31":[["            sw.Stop();                                                                                                                    ",{}]],"32":[["                                                                                                                                          ",{}]],"33":[["            Console.WriteLine(\"Total: \" + total);                                                                                         ",{}]],"34":[["            Console.WriteLine(\"Took \" + sw.ElapsedMilliseconds + \"ms!\");                                                                  ",{}]],"35":[["            Console.WriteLine(\"\");                                                                                                        ",{}]],"36":[["                                                                                                                                          ",{}]],"38":[["        }                                                                                                                                 ",{}]],"39":[["    }                                                                                                                                     ",{}]],"40":[["}                                                                                                                                         ",{}]],"41":[["tv@apu:~/src/erlisch$ msc Program.cs                                                                                                      ",{}]],"42":[["No command 'msc' found, but there are 22 similar ones                                                                                     ",{}]],"43":[["msc: command not found                                                                                                                    ",{}]],"44":[["tv@apu:~/src/erlisch$ mcs Program.cs                                                                                                      ",{}]],"45":[["                                                                                                                                          ",{}]]},"cursor":{"x":0}}],[0.447076,{"lines":{"45":[["tv@apu:~/src/erlisch$                                                                                                                     ",{}]]},"cursor":{"x":22}}],[0.690765,{"lines":{"45":[["tv@apu:~/src/erlisch$ .                                                                                                                   ",{}]]},"cursor":{"x":23}}],[0.275442,{"lines":{"45":[["tv@apu:~/src/erlisch$ ./                                                                                                                  ",{}]]},"cursor":{"x":24}}],[0.472599,{"lines":{"45":[["tv@apu:~/src/erlisch$ ./P                                                                                                                 ",{}]]},"cursor":{"x":25}}],[0.243014,{"lines":{"45":[["tv@apu:~/src/erlisch$ ./Program.exe                                                                                                       ",{}]]},"cursor":{"x":36}}],[0.6827029999999999,{"lines":{"0":[["                                                                                                                                          ",{}]],"1":[["100%[================================================================================================>] 880         --.-K/s   in 0s       ",{}]],"2":[["                                                                                                                                          ",{}]],"3":[["2014-09-06 18:21:42 (133 MB/s) - ‘Program.cs’ saved [880/880]                                                                             ",{}]],"4":[["                                                                                                                                          ",{}]],"5":[["tv@apu:~/src/erlisch$ cat Program.cs                                                                                                      ",{}]],"6":[["using System;                                                                                                                             ",{}]],"7":[["using System.Collections.Generic;                                                                                                         ",{}]],"8":[["using System.Diagnostics;                                                                                                                 ",{}]],"9":[["                                                                                                                                          ",{}]],"10":[["namespace TestForKvisle {                                                                                                                 ",{}]],"11":[["    class Program {                                                                                                                       ",{}]],"12":[["        static void Main(string[] args) {                                                                                                 ",{}]],"13":[["            int total = 0;                                                                                                                ",{}]],"14":[["            Stopwatch sw = new Stopwatch();                                                                                               ",{}]],"15":[["            List<int> list = new List<int>();                                                                                             ",{}]],"16":[["                                                                                                                                          ",{}]],"17":[["            Console.WriteLine(\"Hello Kvisle\");                                                                                            ",{}]],"18":[["                                                                                                                                          ",{}]],"19":[["            for (int i = 1; i <= 1000000; ++i) {                                                                                          ",{}]],"20":[["                list.Add(i);                                                                                                              ",{}]],"21":[["            }                                                                                                                             ",{}]],"22":[["                                                                                                                                          ",{}]],"23":[["            sw.Start();                                                                                                                   ",{}]],"24":[["            /*foreach (int i in list) {                                                                                                   ",{}]],"25":[["                total += i;                                                                                                               ",{}]],"26":[["            }*/                                                                                                                           ",{}]],"27":[["            for (int i = 0; i < list.Count; ++i) {                                                                                        ",{}]],"28":[["                total += list[i];                                                                                                         ",{}]],"29":[["            }                                                                                                                             ",{}]],"30":[["            sw.Stop();                                                                                                                    ",{}]],"31":[["                                                                                                                                          ",{}]],"32":[["            Console.WriteLine(\"Total: \" + total);                                                                                         ",{}]],"33":[["            Console.WriteLine(\"Took \" + sw.ElapsedMilliseconds + \"ms!\");                                                                  ",{}]],"34":[["            Console.WriteLine(\"\");                                                                                                        ",{}]],"35":[["                                                                                                                                          ",{}]],"37":[["        }                                                                                                                                 ",{}]],"38":[["    }                                                                                                                                     ",{}]],"39":[["}                                                                                                                                         ",{}]],"40":[["tv@apu:~/src/erlisch$ msc Program.cs                                                                                                      ",{}]],"41":[["No command 'msc' found, but there are 22 similar ones                                                                                     ",{}]],"42":[["msc: command not found                                                                                                                    ",{}]],"43":[["tv@apu:~/src/erlisch$ mcs Program.cs                                                                                                      ",{}]],"44":[["tv@apu:~/src/erlisch$ ./Program.exe                                                                                                       ",{}]],"45":[["                                                                                                                                          ",{}]]},"cursor":{"x":0}}],[0.025699,{"lines":{"45":[["Hello Kvisle                                                                                                                              ",{}]]},"cursor":{"x":12}}],[0.014811,{"lines":{"1":[["tv@apu:~/src/erlisch$ cat Program.cs                                                                                                      ",{}]],"2":[["using System;                                                                                                                             ",{}]],"3":[["using System.Collections.Generic;                                                                                                         ",{}]],"4":[["using System.Diagnostics;                                                                                                                 ",{}]],"5":[["                                                                                                                                          ",{}]],"6":[["namespace TestForKvisle {                                                                                                                 ",{}]],"7":[["    class Program {                                                                                                                       ",{}]],"8":[["        static void Main(string[] args) {                                                                                                 ",{}]],"9":[["            int total = 0;                                                                                                                ",{}]],"10":[["            Stopwatch sw = new Stopwatch();                                                                                               ",{}]],"11":[["            List<int> list = new List<int>();                                                                                             ",{}]],"12":[["                                                                                                                                          ",{}]],"13":[["            Console.WriteLine(\"Hello Kvisle\");                                                                                            ",{}]],"14":[["                                                                                                                                          ",{}]],"15":[["            for (int i = 1; i <= 1000000; ++i) {                                                                                          ",{}]],"16":[["                list.Add(i);                                                                                                              ",{}]],"17":[["            }                                                                                                                             ",{}]],"19":[["            sw.Start();                                                                                                                   ",{}]],"20":[["            /*foreach (int i in list) {                                                                                                   ",{}]],"21":[["                total += i;                                                                                                               ",{}]],"22":[["            }*/                                                                                                                           ",{}]],"23":[["            for (int i = 0; i < list.Count; ++i) {                                                                                        ",{}]],"24":[["                total += list[i];                                                                                                         ",{}]],"25":[["            }                                                                                                                             ",{}]],"26":[["            sw.Stop();                                                                                                                    ",{}]],"27":[["                                                                                                                                          ",{}]],"28":[["            Console.WriteLine(\"Total: \" + total);                                                                                         ",{}]],"29":[["            Console.WriteLine(\"Took \" + sw.ElapsedMilliseconds + \"ms!\");                                                                  ",{}]],"30":[["            Console.WriteLine(\"\");                                                                                                        ",{}]],"32":[["                                                                                                                                          ",{}]],"33":[["        }                                                                                                                                 ",{}]],"34":[["    }                                                                                                                                     ",{}]],"35":[["}                                                                                                                                         ",{}]],"36":[["tv@apu:~/src/erlisch$ msc Program.cs                                                                                                      ",{}]],"37":[["No command 'msc' found, but there are 22 similar ones                                                                                     ",{}]],"38":[["msc: command not found                                                                                                                    ",{}]],"39":[["tv@apu:~/src/erlisch$ mcs Program.cs                                                                                                      ",{}]],"40":[["tv@apu:~/src/erlisch$ ./Program.exe                                                                                                       ",{}]],"41":[["Hello Kvisle                                                                                                                              ",{}]],"42":[["Total: 1784293664                                                                                                                         ",{}]],"43":[["Took 2ms!                                                                                                                                 ",{}]],"44":[["                                                                                                                                          ",{}]],"45":[["                                                                                                                                          ",{}]]},"cursor":{"x":0}}],[0.00563,{"lines":{"45":[["tv@apu:~/src/erlisch$                                                                                                                     ",{}]]},"cursor":{"x":22}}],[1.846491,{"lines":{"0":[["tv@apu:~/src/erlisch$ cat Program.cs                                                                                                      ",{}]],"1":[["using System;                                                                                                                             ",{}]],"2":[["using System.Collections.Generic;                                                                                                         ",{}]],"3":[["using System.Diagnostics;                                                                                                                 ",{}]],"4":[["                                                                                                                                          ",{}]],"5":[["namespace TestForKvisle {                                                                                                                 ",{}]],"6":[["    class Program {                                                                                                                       ",{}]],"7":[["        static void Main(string[] args) {                                                                                                 ",{}]],"8":[["            int total = 0;                                                                                                                ",{}]],"9":[["            Stopwatch sw = new Stopwatch();                                                                                               ",{}]],"10":[["            List<int> list = new List<int>();                                                                                             ",{}]],"11":[["                                                                                                                                          ",{}]],"12":[["            Console.WriteLine(\"Hello Kvisle\");                                                                                            ",{}]],"13":[["                                                                                                                                          ",{}]],"14":[["            for (int i = 1; i <= 1000000; ++i) {                                                                                          ",{}]],"15":[["                list.Add(i);                                                                                                              ",{}]],"16":[["            }                                                                                                                             ",{}]],"17":[["                                                                                                                                          ",{}]],"18":[["            sw.Start();                                                                                                                   ",{}]],"19":[["            /*foreach (int i in list) {                                                                                                   ",{}]],"20":[["                total += i;                                                                                                               ",{}]],"21":[["            }*/                                                                                                                           ",{}]],"22":[["            for (int i = 0; i < list.Count; ++i) {                                                                                        ",{}]],"23":[["                total += list[i];                                                                                                         ",{}]],"24":[["            }                                                                                                                             ",{}]],"25":[["            sw.Stop();                                                                                                                    ",{}]],"26":[["                                                                                                                                          ",{}]],"27":[["            Console.WriteLine(\"Total: \" + total);                                                                                         ",{}]],"28":[["            Console.WriteLine(\"Took \" + sw.ElapsedMilliseconds + \"ms!\");                                                                  ",{}]],"29":[["            Console.WriteLine(\"\");                                                                                                        ",{}]],"30":[["                                                                                                                                          ",{}]],"32":[["        }                                                                                                                                 ",{}]],"33":[["    }                                                                                                                                     ",{}]],"34":[["}                                                                                                                                         ",{}]],"35":[["tv@apu:~/src/erlisch$ msc Program.cs                                                                                                      ",{}]],"36":[["No command 'msc' found, but there are 22 similar ones                                                                                     ",{}]],"37":[["msc: command not found                                                                                                                    ",{}]],"38":[["tv@apu:~/src/erlisch$ mcs Program.cs                                                                                                      ",{}]],"39":[["tv@apu:~/src/erlisch$ ./Program.exe                                                                                                       ",{}]],"40":[["Hello Kvisle                                                                                                                              ",{}]],"41":[["Total: 1784293664                                                                                                                         ",{}]],"42":[["Took 2ms!                                                                                                                                 ",{}]],"43":[["                                                                                                                                          ",{}]],"44":[["tv@apu:~/src/erlisch$ exit                                                                                                                ",{}]],"45":[["                                                                                                                                          ",{}]]},"cursor":{"x":0}}]]